collibra_catalog_database_registration/__init__.py
collibra_catalog_database_registration/api_client.py
collibra_catalog_database_registration/configuration.py
collibra_catalog_database_registration/rest.py
collibra_catalog_database_registration/api/__init__.py
collibra_catalog_database_registration/api/database_api.py
collibra_catalog_database_registration/api/database_connection_api.py
collibra_catalog_database_registration/api/metadata_api.py
collibra_catalog_database_registration/api/profiling_api.py
collibra_catalog_database_registration/api/schema_connection_api.py
collibra_catalog_database_registration/models/__init__.py
collibra_catalog_database_registration/models/add_database_request.py
collibra_catalog_database_registration/models/add_profiling_configuration_request.py
collibra_catalog_database_registration/models/add_schema_metadata_configuration_batch_request.py
collibra_catalog_database_registration/models/add_schema_metadata_configuration_request.py
collibra_catalog_database_registration/models/add_schema_profiling_configuration_batch_request.py
collibra_catalog_database_registration/models/add_schema_profiling_configuration_request.py
collibra_catalog_database_registration/models/change_database_request.py
collibra_catalog_database_registration/models/change_profiling_configuration_request.py
collibra_catalog_database_registration/models/change_schema_metadata_configuration_request.py
collibra_catalog_database_registration/models/change_schema_profiling_configuration_request.py
collibra_catalog_database_registration/models/database.py
collibra_catalog_database_registration/models/database_connection.py
collibra_catalog_database_registration/models/database_connection_paged_response.py
collibra_catalog_database_registration/models/database_metadata_synchronization_request.py
collibra_catalog_database_registration/models/database_paged_response.py
collibra_catalog_database_registration/models/exclude_types.py
collibra_catalog_database_registration_140-1.4.0.dist-info/METADATA
collibra_catalog_database_registration_140-1.4.0.dist-info/WHEEL
collibra_catalog_database_registration_140-1.4.0.dist-info/top_level.txt
collibra_catalog_database_registration_140-1.4.0.dist-info/RECORD
