Metadata-Version: 2.1
Name: collibra-catalog-database-registration-140
Version: 1.4.0
Summary: Collibra Catalog Database Registration API
Home-page: 
Author-email: 
Keywords: Swagger,Collibra Catalog Database Registration API
Requires-Dist: urllib3 (>=1.15)
Requires-Dist: six (>=1.10)
Requires-Dist: certifi
Requires-Dist: python-dateutil
